{
  "db_id1": 11226,
  "db_id2": 77145,
  "similarity": 0.98999834,
  "cluster1": 9,
  "cluster2": 9,
  "same_cluster": true,
  "database1": {
    "db_id": 11226,
    "wikidata_topic_item_id": "Q76358281",
    "database_name": "TheresienstadtToAuschwitzTransportRecords19441",
    "num_tables": 2,
    "tables": [
      {
        "table_name": "HolocaustVictimsTransportEbRecords",
        "columns": [
          {
            "name": "VictimLabel",
            "type": "string"
          },
          {
            "name": "VictimDescription",
            "type": "string"
          },
          {
            "name": "BirthDate",
            "type": "time"
          },
          {
            "name": "DeathDate",
            "type": "time"
          },
          {
            "name": "EntityType",
            "type": "wikibase-entityid"
          },
          {
            "name": "FirstName",
            "type": "wikibase-entityid"
          },
          {
            "name": "DetentionLocation",
            "type": "wikibase-entityid"
          },
          {
            "name": "LastName",
            "type": "wikibase-entityid"
          },
          {
            "name": "Gender",
            "type": "wikibase-entityid"
          },
          {
            "name": "TransportEvent",
            "type": "wikibase-entityid"
          },
          {
            "name": "TerezinMemorialDatabaseId",
            "type": "string"
          },
          {
            "name": "Role",
            "type": "wikibase-entityid"
          },
          {
            "name": "LastResidence",
            "type": "wikibase-entityid"
          },
          {
            "name": "FullName",
            "type": "monolingualtext"
          },
          {
            "name": "HolocaustczPersonId",
            "type": "string"
          }
        ]
      },
      {
        "table_name": "HolocaustTransportRecords",
        "columns": [
          {
            "name": "TransportLabel",
            "type": "string"
          },
          {
            "name": "TransportDescription",
            "type": "string"
          },
          {
            "name": "DepartureLocation",
            "type": "wikibase-entityid"
          },
          {
            "name": "DeportationDatabaseTransportId",
            "type": "string"
          },
          {
            "name": "DepartureTime",
            "type": "time"
          },
          {
            "name": "ArrivalLocation",
            "type": "wikibase-entityid"
          },
          {
            "name": "TransportType",
            "type": "wikibase-entityid"
          },
          {
            "name": "NumberOfPrisoners",
            "type": "quantity"
          },
          {
            "name": "OriginCountry",
            "type": "wikibase-entityid"
          },
          {
            "name": "ArrivalTime",
            "type": "time"
          }
        ]
      }
    ],
    "all_columns": [
      "arrivaltime",
      "departuretime",
      "departurelocation",
      "deportationdatabasetransportid",
      "origincountry",
      "lastresidence",
      "deathdate",
      "terezinmemorialdatabaseid",
      "detentionlocation",
      "victimdescription",
      "holocaustczpersonid",
      "gender",
      "arrivallocation",
      "transportdescription",
      "transportevent",
      "lastname",
      "entitytype",
      "numberofprisoners",
      "birthdate",
      "transportlabel",
      "transporttype",
      "fullname",
      "role",
      "victimlabel",
      "firstname"
    ],
    "max_rows": 2218
  },
  "database2": {
    "db_id": 77145,
    "wikidata_topic_item_id": "Q76358071",
    "database_name": "theresienstadt_to_auschwitz_transport_records_1943_2",
    "num_tables": 2,
    "tables": [
      {
        "table_name": "holocaust_victims_transport_dr_records",
        "columns": [
          {
            "name": "victim_label",
            "type": "string"
          },
          {
            "name": "victim_description",
            "type": "string"
          },
          {
            "name": "birth_date",
            "type": "time"
          },
          {
            "name": "death_date",
            "type": "time"
          },
          {
            "name": "entity_type",
            "type": "wikibase-entityid"
          },
          {
            "name": "first_name",
            "type": "wikibase-entityid"
          },
          {
            "name": "detention_location",
            "type": "wikibase-entityid"
          },
          {
            "name": "gender",
            "type": "wikibase-entityid"
          },
          {
            "name": "last_name",
            "type": "wikibase-entityid"
          },
          {
            "name": "terezin_memorial_database_id",
            "type": "string"
          },
          {
            "name": "transport_event",
            "type": "wikibase-entityid"
          },
          {
            "name": "role",
            "type": "wikibase-entityid"
          },
          {
            "name": "last_residence",
            "type": "wikibase-entityid"
          },
          {
            "name": "full_name",
            "type": "monolingualtext"
          },
          {
            "name": "holocaustcz_person_id",
            "type": "string"
          }
        ]
      },
      {
        "table_name": "holocaust_transport_records",
        "columns": [
          {
            "name": "transport_label",
            "type": "string"
          },
          {
            "name": "transport_description",
            "type": "string"
          },
          {
            "name": "transport_type",
            "type": "wikibase-entityid"
          },
          {
            "name": "departure_time",
            "type": "time"
          },
          {
            "name": "arrival_time",
            "type": "time"
          },
          {
            "name": "departure_location",
            "type": "wikibase-entityid"
          },
          {
            "name": "arrival_location",
            "type": "wikibase-entityid"
          },
          {
            "name": "number_of_prisoners",
            "type": "quantity"
          },
          {
            "name": "governing_country",
            "type": "wikibase-entityid"
          },
          {
            "name": "deportation_database_transport_id",
            "type": "string"
          }
        ]
      }
    ],
    "all_columns": [
      "arrivaltime",
      "departuretime",
      "departurelocation",
      "governingcountry",
      "deportationdatabasetransportid",
      "lastresidence",
      "deathdate",
      "terezinmemorialdatabaseid",
      "detentionlocation",
      "victimdescription",
      "holocaustczpersonid",
      "gender",
      "arrivallocation",
      "transportdescription",
      "transportevent",
      "lastname",
      "entitytype",
      "numberofprisoners",
      "birthdate",
      "transportlabel",
      "transporttype",
      "fullname",
      "role",
      "victimlabel",
      "firstname"
    ],
    "max_rows": 2268
  },
  "common_columns": [
    "arrivaltime",
    "departuretime",
    "departurelocation",
    "deportationdatabasetransportid",
    "lastresidence",
    "deathdate",
    "terezinmemorialdatabaseid",
    "detentionlocation",
    "victimdescription",
    "holocaustczpersonid",
    "gender",
    "arrivallocation",
    "transportdescription",
    "transportevent",
    "lastname",
    "entitytype",
    "numberofprisoners",
    "birthdate",
    "transportlabel",
    "transporttype",
    "fullname",
    "role",
    "victimlabel",
    "firstname"
  ],
  "num_common_columns": 24
}